Metadata-Version: 2.1
Name: summarizer4u
Version: 0.3
Summary: Get your text summarized
Home-page: https://github.com/Navan0
Author: Navaneeth KT
Author-email: nktclt@gmail.com
License: UNKNOWN
Platform: UNKNOWN
